simplecsvdataset/randomaccess.py
simplecsvdataset/whereami.py
simplecsvdataset-0.0.1.dist-info/LICENSE
simplecsvdataset-0.0.1.dist-info/METADATA
simplecsvdataset-0.0.1.dist-info/WHEEL
simplecsvdataset-0.0.1.dist-info/entry_points.txt
simplecsvdataset-0.0.1.dist-info/top_level.txt
simplecsvdataset-0.0.1.dist-info/RECORD
